boilrpy/__init__.py
boilrpy/__main__.py
boilrpy/cli.py
boilrpy/config.py
boilrpy/decorators/_init__.py
boilrpy/decorators/color_decorator.py
boilrpy/dependency_creators/__init__.py
boilrpy/dependency_creators/base_dependency_creator.py
boilrpy/dependency_creators/checker.py
boilrpy/dependency_creators/conda_creator.py
boilrpy/dependency_creators/factory.py
boilrpy/dependency_creators/pip_creator.py
boilrpy/dependency_creators/poetry_creator.py
boilrpy/dependency_creators/uv_creator.py
boilrpy/file_generator.py
boilrpy/file_generators/__init__.py
boilrpy/file_generators/base_generator.py
boilrpy/file_generators/changelog_generator.py
boilrpy/file_generators/dockerfile_generator.py
boilrpy/file_generators/flask_generator.py
boilrpy/file_generators/gitignore_generator.py
boilrpy/file_generators/license_generator.py
boilrpy/file_generators/main_file_generator.py
boilrpy/file_generators/pylint_generator.py
boilrpy/file_generators/readme_generator.py
boilrpy/file_generators/requirements_generator.py
boilrpy/file_writer.py
boilrpy/flask_app_creator.py
boilrpy/input_validator.py
boilrpy/project_creator.py
boilrpy/utils/__init__.py
boilrpy/utils/string_formatter.py
boilrpy-0.8.0.dist-info/entry_points.txt
boilrpy-0.8.0.dist-info/licenses/LICENSE
boilrpy-0.8.0.dist-info/METADATA
boilrpy-0.8.0.dist-info/WHEEL
boilrpy-0.8.0.dist-info/RECORD
