Metadata-Version: 2.4
Name: boilrpy
Version: 0.8.0
Summary: A python development boilerplate generator
License: MIT
License-File: LICENSE
Author: Jean-Michel LIEVIN
Author-email: jeanmichel.liev1@gmail.com
Requires-Python: >=3.11,<4.0
Classifier: License :: OSI Approved :: MIT License
Classifier: Operating System :: OS Independent
Classifier: Programming Language :: Python :: 3
Classifier: Programming Language :: Python :: 3.11
Classifier: Programming Language :: Python :: 3.12
Classifier: Programming Language :: Python :: 3.13
Classifier: Programming Language :: Python :: 3.14
Requires-Dist: colorama (>=0.4.6,<0.5.0)
Requires-Dist: flask (>=3.1.0,<4.0.0)
Requires-Dist: python-dotenv (>=1.0.1,<2.0.0)
Requires-Dist: toml (>=0.10.2,<0.11.0)
